[{"companyName":"Bloombase Canada Inc.","roleName":"software development manager","location":"Vancouver","salaryRange":"CA$100K - CA$120K ","jobLink":"https://glassdoor.com/partner/jobListing.htm?pos=101&ao=1136043&s=58&guid=00000186e990250c8e03ec7b956c3741&src=GD_JOB_AD&t=SR&vt=w&cs=1_f0cd2d52&cb=1678955783774&jobListingId=1008532092963&jrtk=3-0-1grkp099b34ag001-1grkp09a12a83000-2ca66b54924ea4b7-","companyRating":"5","easyApply":false,"jobAge":"24h"},{"companyName":"Smile DH","roleName":"Software Developer, Senior - Remote, Canada","location":"Vancouver","salaryRange":"","jobLink":"https://glassdoor.com/partner/jobListing.htm?pos=102&ao=1136043&s=58&guid=00000186e990250c8e03ec7b956c3741&src=GD_JOB_AD&t=SR&vt=w&ea=1&cs=1_58754ef9&cb=1678955783774&jobListingId=1008531973512&jrtk=3-0-1grkp099b34ag001-1grkp09a12a83000-5e9babd7fe306234-","companyRating":"","easyApply":true,"jobAge":"24h"},{"companyName":"IBI Group","roleName":"Architect Graduate/ Intern Architect - Vancouver Office","location":"Vancouver","salaryRange":"CA$63K - CA$67K ","jobLink":"https://glassdoor.com/partner/jobListing.htm?pos=103&ao=1136043&s=58&guid=00000186e990250c8e03ec7b956c3741&src=GD_JOB_AD&t=SR&vt=w&cs=1_021a4c3e&cb=1678955783774&jobListingId=1008531987963&jrtk=3-0-1grkp099b34ag001-1grkp09a12a83000-e3f3cf6b9f61f5d9-","companyRating":"3.9","easyApply":false,"jobAge":"24h"},{"companyName":"BC Pension Corporation","roleName":"Intermediate Software Developer Database Development","location":"Victoria","salaryRange":"CA$74K - CA$84K ","jobLink":"https://glassdoor.com/partner/jobListing.htm?pos=104&ao=1136043&s=58&guid=00000186e990250c8e03ec7b956c3741&src=GD_JOB_AD&t=SR&vt=w&ea=1&cs=1_683c7168&cb=1678955783774&jobListingId=1008531868363&jrtk=3-0-1grkp099b34ag001-1grkp09a12a83000-eaf2c626e7ebcefd-","companyRating":"4.3","easyApply":true,"jobAge":"24h"},{"companyName":"Beyond Physiotherapy","roleName":"Administrative Assistant","location":"Surrey","salaryRange":"CA$18.00 - CA$22.00 Per Hour","jobLink":"https://glassdoor.com/partner/jobListing.htm?pos=105&ao=1136043&s=58&guid=00000186e990250c8e03ec7b956c3741&src=GD_JOB_AD&t=SR&vt=w&ea=1&cs=1_ac1ccbc9&cb=1678955783774&jobListingId=1008532010420&jrtk=3-0-1grkp099b34ag001-1grkp09a12a83000-7736c568fc809877-","companyRating":"","easyApply":true,"jobAge":"24h"},{"companyName":"Fasken","roleName":"CRM Database Coordinator","location":"Vancouver","salaryRange":"CA$47K - CA$52K ","jobLink":"https://glassdoor.com/partner/jobListing.htm?pos=106&ao=1136043&s=58&guid=00000186e990250c8e03ec7b956c3741&src=GD_JOB_AD&t=SR&vt=w&ea=1&cs=1_9e8da78c&cb=1678955783774&jobListingId=1008531753267&jrtk=3-0-1grkp099b34ag001-1grkp09a12a83000-4711cc06a6236c11-","companyRating":"3.5","easyApply":true,"jobAge":"24h"},{"companyName":"Kron Technologies Inc.","roleName":"IT Business Analyst (FT)","location":"Burnaby","salaryRange":"CA$79K - CA$95K ","jobLink":"https://glassdoor.com/partner/jobListing.htm?pos=107&ao=1136043&s=58&guid=00000186e990250c8e03ec7b956c3741&src=GD_JOB_AD&t=SR&vt=w&ea=1&cs=1_db6364db&cb=1678955783774&jobListingId=1008532248899&jrtk=3-0-1grkp099b34ag001-1grkp09a12a83000-daf431f6c0c44484-","companyRating":"3.1","easyApply":true,"jobAge":"24h"},{"companyName":"IBI Group","roleName":"Architect Graduate/Intern Architect - Vancouver Office","location":"Burnaby","salaryRange":"CA$63K - CA$67K ","jobLink":"https://glassdoor.com/partner/jobListing.htm?pos=108&ao=1136043&s=58&guid=00000186e990250c8e03ec7b956c3741&src=GD_JOB_AD&t=SR&vt=w&cs=1_184c4bce&cb=1678955783774&jobListingId=1008531987888&jrtk=3-0-1grkp099b34ag001-1grkp09a12a83000-421f6ebe96e24af0-","companyRating":"3.9","easyApply":false,"jobAge":"24h"},{"companyName":"School District #47 (Powell River)","roleName":"Executive Assistant","location":"Powell River","salaryRange":"CA$57K - CA$81K ","jobLink":"https://glassdoor.com/partner/jobListing.htm?pos=109&ao=1136043&s=58&guid=00000186e990250c8e03ec7b956c3741&src=GD_JOB_AD&t=SR&vt=w&cs=1_5223fad5&cb=1678955783774&jobListingId=1008531981804&jrtk=3-0-1grkp099b34ag001-1grkp09a12a83000-bcb2f4dc89705df7-","companyRating":"4","easyApply":false,"jobAge":"24h"},{"companyName":"Ignite Technical Resources.","roleName":"Sr. Power Platform & Dynamics 365 Dev [BHJOB13022_12664]","location":"Vancouver","salaryRange":"","jobLink":"https://glassdoor.com/partner/jobListing.htm?pos=110&ao=1136043&s=58&guid=00000186e990250c8e03ec7b956c3741&src=GD_JOB_AD&t=SR&vt=w&ea=1&cs=1_483c4692&cb=1678955783775&jobListingId=1008531697913&jrtk=3-0-1grkp099b34ag001-1grkp09a12a83000-b6a85b737056093c-","companyRating":"4.8","easyApply":true,"jobAge":"24h"},{"companyName":"Xplor","roleName":"Senior Site Reliability Engineer","location":"Vancouver","salaryRange":"CA$80K - CA$140K ","jobLink":"https://glassdoor.com/partner/jobListing.htm?pos=111&ao=1136043&s=58&guid=00000186e990250c8e03ec7b956c3741&src=GD_JOB_AD&t=SR&vt=w&cs=1_093d70d5&cb=1678955783775&jobListingId=1008531990871&jrtk=3-0-1grkp099b34ag001-1grkp09a12a83000-444a74f9dacc947a-","companyRating":"3.8","easyApply":false,"jobAge":"24h"},{"companyName":"Vizzion","roleName":"Software Engineer","location":"North Vancouver","salaryRange":"CA$25.00 - CA$50.00 Per Hour","jobLink":"https://glassdoor.com/partner/jobListing.htm?pos=112&ao=1136043&s=58&guid=00000186e990250c8e03ec7b956c3741&src=GD_JOB_AD&t=SR&vt=w&cs=1_44fdb48c&cb=1678955783775&jobListingId=1008531350168&jrtk=3-0-1grkp099b34ag001-1grkp09a12a83000-be655f62e701ab34-","companyRating":"4.4","easyApply":false,"jobAge":"24h"},{"companyName":"RABBIT FEET ENTERTAINMENT INC.","roleName":"software developer","location":"Richmond","salaryRange":"CA$50.00 Per Hour","jobLink":"https://glassdoor.com/partner/jobListing.htm?pos=113&ao=1136043&s=58&guid=00000186e990250c8e03ec7b956c3741&src=GD_JOB_AD&t=SR&vt=w&cs=1_187929c8&cb=1678955783775&jobListingId=1008531373160&jrtk=3-0-1grkp099b34ag001-1grkp09a12a83000-cc6c0eb6eedc2e59-","companyRating":"","easyApply":false,"jobAge":"24h"},{"companyName":"Rainforest Automation","roleName":"Software Tester and Technical Support","location":"Vancouver","salaryRange":"","jobLink":"https://glassdoor.com/partner/jobListing.htm?pos=114&ao=1136043&s=58&guid=00000186e990250c8e03ec7b956c3741&src=GD_JOB_AD&t=SR&vt=w&ea=1&cs=1_7053b5a7&cb=1678955783775&jobListingId=1008531295115&jrtk=3-0-1grkp099b34ag001-1grkp09a12a83000-b29146cedbdf095a-","companyRating":"","easyApply":true,"jobAge":"24h"},{"companyName":"University of British Columbia","roleName":"Systems Analyst II","location":"Vancouver","salaryRange":"CA$6K - CA$9K ","jobLink":"https://glassdoor.com/partner/jobListing.htm?pos=115&ao=1136043&s=58&guid=00000186e990250c8e03ec7b956c3741&src=GD_JOB_AD&t=SR&vt=w&cs=1_3a1da1d1&cb=1678955783775&jobListingId=1008531633915&jrtk=3-0-1grkp099b34ag001-1grkp09a12a83000-1b766f7d62013010-","companyRating":"4.2","easyApply":false,"jobAge":"24h"},{"companyName":"Vizzion","roleName":"Software Engineering Manager","location":"North Vancouver","salaryRange":"CA$80K - CA$140K ","jobLink":"https://glassdoor.com/partner/jobListing.htm?pos=116&ao=1136043&s=58&guid=00000186e990250c8e03ec7b956c3741&src=GD_JOB_AD&t=SR&vt=w&cs=1_b0c22779&cb=1678955783775&jobListingId=1008531331908&jrtk=3-0-1grkp099b34ag001-1grkp09a12a83000-e31ad8db615c5082-","companyRating":"4.4","easyApply":false,"jobAge":"24h"},{"companyName":"Vancouver Patrolling Security Ltd","roleName":"Web designer","location":"Surrey","salaryRange":"CA$32.50 Per Hour","jobLink":"https://glassdoor.com/partner/jobListing.htm?pos=117&ao=1136043&s=58&guid=00000186e990250c8e03ec7b956c3741&src=GD_JOB_AD&t=SR&vt=w&cs=1_320d995d&cb=1678955783776&jobListingId=1008531373000&jrtk=3-0-1grkp099b34ag001-1grkp09a12a83000-54fc8f10883a4e19-","companyRating":"","easyApply":false,"jobAge":"24h"},{"companyName":"Staffbase","roleName":"Quality Assurance Engineer - Temporary Fixed Term (12 Months)","location":"Vancouver","salaryRange":"","jobLink":"https://glassdoor.com/partner/jobListing.htm?pos=118&ao=1136043&s=58&guid=00000186e990250c8e03ec7b956c3741&src=GD_JOB_AD&t=SR&vt=w&ea=1&cs=1_6bc5f4ef&cb=1678955783776&jobListingId=1008531426685&jrtk=3-0-1grkp099b34ag001-1grkp09a12a83000-f22b90502669aa6c-","companyRating":"4.2","easyApply":true,"jobAge":"24h"},{"companyName":"IKEA","roleName":"Technical Support Specialist (On-Site)","location":"Richmond","salaryRange":"CA$50K - CA$54K ","jobLink":"https://glassdoor.com/partner/jobListing.htm?pos=119&ao=1136043&s=58&guid=00000186e990250c8e03ec7b956c3741&src=GD_JOB_AD&t=SR&vt=w&cs=1_c3fe0568&cb=1678955783776&jobListingId=1008531487808&jrtk=3-0-1grkp099b34ag001-1grkp09a12a83000-db01fb1e6c145c8a-","companyRating":"3.9","easyApply":false,"jobAge":"24h"},{"companyName":"Asco Aerospace Canada Ltd.","roleName":"IT Systems Administrator","location":"Delta","salaryRange":"CA$75K - CA$95K ","jobLink":"https://glassdoor.com/partner/jobListing.htm?pos=120&ao=1136043&s=58&guid=00000186e990250c8e03ec7b956c3741&src=GD_JOB_AD&t=SR&vt=w&cs=1_b02ad0a7&cb=1678955783776&jobListingId=1008530998336&jrtk=3-0-1grkp099b34ag001-1grkp09a12a83000-3a6712e7d1807386-","companyRating":"3.5","easyApply":false,"jobAge":"24h"},{"companyName":"Fortinet","roleName":"Senior Software Developer","location":"Burnaby","salaryRange":"CA$85K - CA$108K ","jobLink":"https://glassdoor.com/partner/jobListing.htm?pos=121&ao=1136043&s=58&guid=00000186e990250c8e03ec7b956c3741&src=GD_JOB_AD&t=SR&vt=w&cs=1_6f634487&cb=1678955783776&jobListingId=1008531634745&jrtk=3-0-1grkp099b34ag001-1grkp09a12a83000-c8d6cf4a81e52468-","companyRating":"4","easyApply":false,"jobAge":"24h"},{"companyName":"Chinese Presbyterian Church","roleName":"church secretary","location":"Vancouver","salaryRange":"CA$19.00 - CA$25.00 Per Hour","jobLink":"https://glassdoor.com/partner/jobListing.htm?pos=122&ao=1136043&s=58&guid=00000186e990250c8e03ec7b956c3741&src=GD_JOB_AD&t=SR&vt=w&cs=1_b93c608e&cb=1678955783776&jobListingId=1008531372890&jrtk=3-0-1grkp099b34ag001-1grkp09a12a83000-6ffc8807fc24a969-","companyRating":"4","easyApply":false,"jobAge":"24h"},{"companyName":"D3 Security","roleName":"Intermediate / Senior Database Developer and Administrator","location":"Vancouver","salaryRange":"CA$56K - CA$78K ","jobLink":"https://glassdoor.com/partner/jobListing.htm?pos=123&ao=1136043&s=58&guid=00000186e990250c8e03ec7b956c3741&src=GD_JOB_AD&t=SR&vt=w&ea=1&cs=1_12185bc9&cb=1678955783776&jobListingId=1008531307038&jrtk=3-0-1grkp099b34ag001-1grkp09a12a83000-87af66dbe03e47ff-","companyRating":"3.8","easyApply":true,"jobAge":"24h"},{"companyName":"Fortinet","roleName":"Technical Support Expert","location":"Burnaby","salaryRange":"CA$74K - CA$87K ","jobLink":"https://glassdoor.com/partner/jobListing.htm?pos=124&ao=1136043&s=58&guid=00000186e990250c8e03ec7b956c3741&src=GD_JOB_AD&t=SR&vt=w&cs=1_09ae9a58&cb=1678955783776&jobListingId=1008531634765&jrtk=3-0-1grkp099b34ag001-1grkp09a12a83000-400b897906444935-","companyRating":"4","easyApply":false,"jobAge":"24h"},{"companyName":"Fortinet","roleName":"Golang Software Developer","location":"Burnaby","salaryRange":"CA$85K - CA$108K ","jobLink":"https://glassdoor.com/partner/jobListing.htm?pos=125&ao=1136043&s=58&guid=00000186e990250c8e03ec7b956c3741&src=GD_JOB_AD&t=SR&vt=w&cs=1_961e21ff&cb=1678955783776&jobListingId=1008531634704&jrtk=3-0-1grkp099b34ag001-1grkp09a12a83000-1d38023800bd3fa9-","companyRating":"4","easyApply":false,"jobAge":"24h"},{"companyName":"Cash Cowboy","roleName":"Administrative Assistant","location":"Vancouver","salaryRange":"CA$17.00 - CA$25.00 Per Hour","jobLink":"https://glassdoor.com/partner/jobListing.htm?pos=126&ao=1136043&s=58&guid=00000186e990250c8e03ec7b956c3741&src=GD_JOB_AD&t=SR&vt=w&ea=1&cs=1_90db98d6&cb=1678955783776&jobListingId=1008531084372&jrtk=3-0-1grkp099b34ag001-1grkp09a12a83000-0aa44c3e39216683-","companyRating":"","easyApply":true,"jobAge":"24h"},{"companyName":"VANSTARS EDUCATION LTD","roleName":"Full-Time Administrative Assistant","location":"Richmond","salaryRange":"CA$18.00 - CA$25.00 Per Hour","jobLink":"https://glassdoor.com/partner/jobListing.htm?pos=127&ao=1136043&s=58&guid=00000186e990250c8e03ec7b956c3741&src=GD_JOB_AD&t=SR&vt=w&ea=1&cs=1_e7edc176&cb=1678955783776&jobListingId=1008531368980&jrtk=3-0-1grkp099b34ag001-1grkp09a12a83000-5ac5375c9ffd6f30-","companyRating":"","easyApply":true,"jobAge":"24h"},{"companyName":"123Dentist","roleName":"Executive Assistant","location":"Burnaby","salaryRange":"","jobLink":"https://glassdoor.com/partner/jobListing.htm?pos=128&ao=1136043&s=58&guid=00000186e990250c8e03ec7b956c3741&src=GD_JOB_AD&t=SR&vt=w&ea=1&cs=1_b40450ae&cb=1678955783776&jobListingId=1008531369275&jrtk=3-0-1grkp099b34ag001-1grkp09a12a83000-1d82cf1bc967988a-","companyRating":"3.6","easyApply":true,"jobAge":"24h"},{"companyName":"D3 Security","roleName":"Intermediate / Senior Middle Layer Software Developer","location":"Vancouver","salaryRange":"CA$56K - CA$76K ","jobLink":"https://glassdoor.com/partner/jobListing.htm?pos=129&ao=1136043&s=58&guid=00000186e990250c8e03ec7b956c3741&src=GD_JOB_AD&t=SR&vt=w&ea=1&cs=1_65ce7647&cb=1678955783776&jobListingId=1008531297147&jrtk=3-0-1grkp099b34ag001-1grkp09a12a83000-584f3b15b044858e-","companyRating":"3.8","easyApply":true,"jobAge":"24h"},{"companyName":"ACV Auctions","roleName":"Vice President Information Security","location":"Vancouver","salaryRange":"CA$75K - CA$143K ","jobLink":"https://glassdoor.com/partner/jobListing.htm?pos=130&ao=1136043&s=58&guid=00000186e990250c8e03ec7b956c3741&src=GD_JOB_AD&t=SR&vt=w&ea=1&cs=1_8ffb5077&cb=1678955783776&jobListingId=1008531440621&jrtk=3-0-1grkp099b34ag001-1grkp09a12a83000-45e040b24aa853d7-","companyRating":"3.6","easyApply":true,"jobAge":"24h"}]